{
  "twitter": [
    {
      "date": 1581314412270,
      "count": "28"
    },
    {
      "date": 1581307216843,
      "count": "28"
    },
    {
      "date": 1581305416993,
      "count": "28"
    },
    {
      "date": 1581303617771,
      "count": "28"
    },
    {
      "date": 1581262214908,
      "count": "28"
    },
    {
      "date": 1581261192663,
      "count": "28"
    },
    {
      "date": 1581261135528,
      "count": "28"
    },
    {
      "date": 1581239175125,
      "count": "28"
    },
    {
      "date": 1581238577200,
      "count": "28"
    },
    {
      "date": 1581238516283,
      "count": "28"
    },
    {
      "date": 1581238457638,
      "count": "28"
    },
    {
      "date": 1581238328420,
      "count": "28"
    },
    {
      "date": 1581238269138,
      "count": "28"
    },
    {
      "date": 1581238208909,
      "count": "28"
    },
    {
      "date": 1581238149963,
      "count": "28"
    },
    {
      "date": 1581238088587,
      "count": "28"
    },
    {
      "date": 1581238028862,
      "count": "28"
    },
    {
      "date": 1581237011256,
      "count": "28"
    },
    {
      "date": 1581131165419,
      "count": "28"
    },
    {
      "date": 1581131106683,
      "count": "28"
    },
    {
      "date": 1581316217016,
      "count": "28"
    },
    {
      "date": 1581391820401,
      "count": "28"
    },
    {
      "date": 1582255093391,
      "count": "28"
    },
    {
      "date": 1582255152852,
      "count": "28"
    },
    {
      "date": 1582255212920,
      "count": "28"
    },
    {
      "date": 1582255272464,
      "count": "28"
    },
    {
      "date": 1582255816427,
      "count": "28"
    },
    {
      "date": 1582256413182,
      "count": "28"
    },
    {
      "date": 1582257016094,
      "count": "28"
    },
    {
      "date": 1582257617508,
      "count": "28"
    },
    {
      "date": 1582258094209,
      "count": "28"
    },
    {
      "date": 1582258153035,
      "count": "28"
    },
    {
      "date": 1584193218672,
      "count": "29"
    },
    {
      "date": 1584193272782,
      "count": "29"
    },
    {
      "date": 1584193334321,
      "count": "29"
    },
    {
      "date": 1584193392538,
      "count": "29"
    },
    {
      "date": 1584193452485,
      "count": "29"
    },
    {
      "date": 1584193512899,
      "count": "29"
    },
    {
      "date": 1584193572741,
      "count": "29"
    },
    {
      "date": 1584193632414,
      "count": "29"
    },
    {
      "date": 1584193692724,
      "count": "29"
    },
    {
      "date": 1584193752539,
      "count": "29"
    },
    {
      "date": 1584193812607,
      "count": "29"
    },
    {
      "date": 1584193872617,
      "count": "29"
    },
    {
      "date": 1584193932534,
      "count": "29"
    },
    {
      "date": 1584193992640,
      "count": "29"
    },
    {
      "date": 1584194053115,
      "count": "29"
    },
    {
      "date": 1584194112526,
      "count": "29"
    },
    {
      "date": 1584194172832,
      "count": "29"
    },
    {
      "date": 1584194232550,
      "count": "29"
    },
    {
      "date": 1584194292609,
      "count": "29"
    },
    {
      "date": 1584194352438,
      "count": "29"
    },
    {
      "date": 1584194412661,
      "count": "29"
    },
    {
      "date": 1584194472239,
      "count": "29"
    },
    {
      "date": 1584194652482,
      "count": "29"
    },
    {
      "date": 1584194712462,
      "count": "29"
    },
    {
      "date": 1584194772573,
      "count": "29"
    },
    {
      "date": 1584194832451,
      "count": "29"
    },
    {
      "date": 1584194952369,
      "count": "29"
    },
    {
      "date": 1584195012542,
      "count": "29"
    },
    {
      "date": 1584195072585,
      "count": "29"
    },
    {
      "date": 1584195192102,
      "count": "29"
    },
    {
      "date": 1584195314220,
      "count": "29"
    },
    {
      "date": 1584195373276,
      "count": "29"
    },
    {
      "date": 1584195431513,
      "count": "29"
    },
    {
      "date": 1584195493023,
      "count": "29"
    },
    {
      "date": 1584195553082,
      "count": "29"
    },
    {
      "date": 1584195610986,
      "count": "29"
    },
    {
      "date": 1584195671310,
      "count": "29"
    },
    {
      "date": 1584195730814,
      "count": "29"
    },
    {
      "date": 1584195792767,
      "count": "29"
    },
    {
      "date": 1584195852249,
      "count": "29"
    },
    {
      "date": 1584195912674,
      "count": "29"
    },
    {
      "date": 1584195972508,
      "count": "29"
    },
    {
      "date": 1584196033014,
      "count": "29"
    },
    {
      "date": 1584196092895,
      "count": "29"
    },
    {
      "date": 1584196152826,
      "count": "29"
    },
    {
      "date": 1584196212753,
      "count": "29"
    },
    {
      "date": 1584196273906,
      "count": "29"
    },
    {
      "date": 1584196332318,
      "count": "29"
    },
    {
      "date": 1584196392779,
      "count": "29"
    },
    {
      "date": 1584196452410,
      "count": "29"
    },
    {
      "date": 1584196512836,
      "count": "29"
    },
    {
      "date": 1584196572262,
      "count": "29"
    },
    {
      "date": 1584196632379,
      "count": "29"
    },
    {
      "date": 1584196692382,
      "count": "29"
    },
    {
      "date": 1584196752517,
      "count": "29"
    },
    {
      "date": 1584196812477,
      "count": "29"
    },
    {
      "date": 1584196873285,
      "count": "29"
    },
    {
      "date": 1584196933021,
      "count": "29"
    },
    {
      "date": 1584196992986,
      "count": "29"
    },
    {
      "date": 1584197052655,
      "count": "29"
    },
    {
      "date": 1584197112878,
      "count": "29"
    },
    {
      "date": 1584197172265,
      "count": "29"
    },
    {
      "date": 1584197231158,
      "count": "29"
    },
    {
      "date": 1584197292544,
      "count": "29"
    },
    {
      "date": 1584197413069,
      "count": "29"
    },
    {
      "date": 1584197472501,
      "count": "29"
    },
    {
      "date": 1584197532324,
      "count": "29"
    },
    {
      "date": 1584197592569,
      "count": "29"
    },
    {
      "date": 1584197652514,
      "count": "29"
    },
    {
      "date": 1584197712473,
      "count": "29"
    },
    {
      "date": 1584197772598,
      "count": "29"
    },
    {
      "date": 1584197832408,
      "count": "29"
    },
    {
      "date": 1584197892540,
      "count": "29"
    },
    {
      "date": 1584197952065,
      "count": "29"
    },
    {
      "date": 1584198012559,
      "count": "29"
    },
    {
      "date": 1584198073737,
      "count": "29"
    },
    {
      "date": 1584198132951,
      "count": "29"
    },
    {
      "date": 1584198192202,
      "count": "29"
    },
    {
      "date": 1584198252466,
      "count": "29"
    },
    {
      "date": 1584198312501,
      "count": "29"
    },
    {
      "date": 1584198372590,
      "count": "29"
    },
    {
      "date": 1584198432468,
      "count": "29"
    },
    {
      "date": 1584198492409,
      "count": "29"
    },
    {
      "date": 1584198552344,
      "count": "29"
    },
    {
      "date": 1584198612252,
      "count": "29"
    },
    {
      "date": 1584198672537,
      "count": "29"
    },
    {
      "date": 1584198732599,
      "count": "29"
    },
    {
      "date": 1584198852560,
      "count": "29"
    },
    {
      "date": 1584198912233,
      "count": "29"
    },
    {
      "date": 1584198972333,
      "count": "29"
    },
    {
      "date": 1584199032814,
      "count": "29"
    },
    {
      "date": 1584199092704,
      "count": "29"
    },
    {
      "date": 1584199152788,
      "count": "29"
    },
    {
      "date": 1584199212470,
      "count": "29"
    },
    {
      "date": 1584199272595,
      "count": "29"
    },
    {
      "date": 1584199332283,
      "count": "29"
    },
    {
      "date": 1584199392106,
      "count": "29"
    },
    {
      "date": 1584199452443,
      "count": "29"
    },
    {
      "date": 1584199512656,
      "count": "29"
    },
    {
      "date": 1584199573011,
      "count": "29"
    },
    {
      "date": 1584199632531,
      "count": "29"
    },
    {
      "date": 1584199692718,
      "count": "29"
    },
    {
      "date": 1584199752505,
      "count": "29"
    },
    {
      "date": 1584199812532,
      "count": "29"
    },
    {
      "date": 1584199872241,
      "count": "29"
    },
    {
      "date": 1584199932592,
      "count": "29"
    },
    {
      "date": 1584199992744,
      "count": "29"
    },
    {
      "date": 1584200052482,
      "count": "29"
    },
    {
      "date": 1584200112874,
      "count": "29"
    },
    {
      "date": 1584200172485,
      "count": "29"
    },
    {
      "date": 1584200232162,
      "count": "29"
    },
    {
      "date": 1584200291159,
      "count": "29"
    },
    {
      "date": 1584200352542,
      "count": "29"
    },
    {
      "date": 1584200472413,
      "count": "29"
    },
    {
      "date": 1584200532598,
      "count": "29"
    },
    {
      "date": 1584200592679,
      "count": "29"
    },
    {
      "date": 1584200652469,
      "count": "29"
    },
    {
      "date": 1584200713202,
      "count": "29"
    },
    {
      "date": 1584200772444,
      "count": "29"
    },
    {
      "date": 1584200893829,
      "count": "29"
    },
    {
      "date": 1584200952376,
      "count": "29"
    },
    {
      "date": 1584201012846,
      "count": "29"
    },
    {
      "date": 1584201072085,
      "count": "29"
    },
    {
      "date": 1584201132180,
      "count": "29"
    },
    {
      "date": 1584201192494,
      "count": "29"
    },
    {
      "date": 1584201252544,
      "count": "29"
    },
    {
      "date": 1584201312103,
      "count": "29"
    },
    {
      "date": 1584201372383,
      "count": "29"
    },
    {
      "date": 1584201432421,
      "count": "29"
    },
    {
      "date": 1584201492800,
      "count": "29"
    },
    {
      "date": 1584201554306,
      "count": "29"
    },
    {
      "date": 1584201612431,
      "count": "29"
    },
    {
      "date": 1584201672611,
      "count": "29"
    },
    {
      "date": 1584201734533,
      "count": "29"
    },
    {
      "date": 1584201792629,
      "count": "29"
    },
    {
      "date": 1584201852442,
      "count": "29"
    },
    {
      "date": 1584202034502,
      "count": "29"
    },
    {
      "date": 1584202092735,
      "count": "29"
    },
    {
      "date": 1584202152645,
      "count": "29"
    },
    {
      "date": 1584202212225,
      "count": "29"
    },
    {
      "date": 1584202272572,
      "count": "29"
    },
    {
      "date": 1584202332394,
      "count": "29"
    },
    {
      "date": 1584202392665,
      "count": "29"
    },
    {
      "date": 1584228437886,
      "count": "29"
    },
    {
      "date": 1584228492366,
      "count": "29"
    },
    {
      "date": 1584228612553,
      "count": "29"
    },
    {
      "date": 1584228672459,
      "count": "29"
    },
    {
      "date": 1584228732456,
      "count": "29"
    },
    {
      "date": 1584228792759,
      "count": "29"
    },
    {
      "date": 1584228852362,
      "count": "29"
    },
    {
      "date": 1584228912622,
      "count": "29"
    },
    {
      "date": 1584228972859,
      "count": "29"
    },
    {
      "date": 1584232214602,
      "count": "29"
    },
    {
      "date": 1584234015025,
      "count": "29"
    },
    {
      "date": 1584235816029,
      "count": "29"
    },
    {
      "date": 1584237614655,
      "count": "29"
    },
    {
      "date": 1584239415337,
      "count": "29"
    },
    {
      "date": 1584241215177,
      "count": "29"
    },
    {
      "date": 1584243014909,
      "count": "29"
    },
    {
      "date": 1584248412721,
      "count": "29"
    },
    {
      "date": 1584250212731,
      "count": "29"
    },
    {
      "date": 1584253812760,
      "count": "29"
    },
    {
      "date": 1584255612882,
      "count": "29"
    },
    {
      "date": 1584257413160,
      "count": "29"
    },
    {
      "date": 1584259212570,
      "count": "29"
    },
    {
      "date": 1584262812594,
      "count": "29"
    },
    {
      "date": 1584264612816,
      "count": "29"
    },
    {
      "date": 1584266413218,
      "count": "29"
    },
    {
      "date": 1584268212277,
      "count": "29"
    },
    {
      "date": 1584271812416,
      "count": "29"
    },
    {
      "date": 1584273612412,
      "count": "29"
    },
    {
      "date": 1584329415561,
      "count": "29"
    },
    {
      "date": 1584331215420,
      "count": "29"
    },
    {
      "date": 1584333017339,
      "count": "29"
    },
    {
      "date": 1584334815553,
      "count": "29"
    },
    {
      "date": 1584338414561,
      "count": "29"
    },
    {
      "date": 1584340214797,
      "count": "29"
    },
    {
      "date": 1584584876912,
      "count": "30"
    },
    {
      "date": 1584587306383,
      "count": "30"
    },
    {
      "date": 1584587335919,
      "count": "30"
    }
  ],
  "instagram": [
    {
      "date": 1581131106684,
      "count": "297"
    },
    {
      "date": 1581131165420,
      "count": "297"
    },
    {
      "date": 1581237011257,
      "count": "296"
    },
    {
      "date": 1581238028863,
      "count": "297"
    },
    {
      "date": 1581238088588,
      "count": "297"
    },
    {
      "date": 1581238149964,
      "count": "297"
    },
    {
      "date": 1581238208910,
      "count": "297"
    },
    {
      "date": 1581238269138,
      "count": "297"
    },
    {
      "date": 1581238328421,
      "count": "297"
    },
    {
      "date": 1581238457639,
      "count": "296"
    },
    {
      "date": 1581238516284,
      "count": "296"
    },
    {
      "date": 1581238577201,
      "count": "296"
    },
    {
      "date": 1581239175126,
      "count": "296"
    },
    {
      "date": 1581261135529,
      "count": "296"
    },
    {
      "date": 1581261192664,
      "count": "296"
    },
    {
      "date": 1581262214910,
      "count": "296"
    },
    {
      "date": 1581303617772,
      "count": "296"
    },
    {
      "date": 1581305416993,
      "count": "296"
    },
    {
      "date": 1581307216844,
      "count": "296"
    },
    {
      "date": 1581314412271,
      "count": "296"
    },
    {
      "date": 1581316217017,
      "count": "296"
    },
    {
      "date": 1581391820402,
      "count": "295"
    },
    {
      "date": 1582255093392,
      "count": "295"
    },
    {
      "date": 1582255152853,
      "count": "295"
    },
    {
      "date": 1582255212920,
      "count": "295"
    },
    {
      "date": 1582255272464,
      "count": "295"
    },
    {
      "date": 1582255816428,
      "count": "295"
    },
    {
      "date": 1582256413183,
      "count": "295"
    },
    {
      "date": 1582257016094,
      "count": "295"
    },
    {
      "date": 1582257617509,
      "count": "295"
    },
    {
      "date": 1582258094210,
      "count": "295"
    },
    {
      "date": 1582258153036,
      "count": "295"
    },
    {
      "date": 1584193218673,
      "count": "299"
    },
    {
      "date": 1584193272782,
      "count": "299"
    },
    {
      "date": 1584193334321,
      "count": "299"
    },
    {
      "date": 1584193392538,
      "count": "299"
    },
    {
      "date": 1584193452485,
      "count": "299"
    },
    {
      "date": 1584193512900,
      "count": "299"
    },
    {
      "date": 1584193572741,
      "count": "299"
    },
    {
      "date": 1584193632415,
      "count": "299"
    },
    {
      "date": 1584193692724,
      "count": "299"
    },
    {
      "date": 1584193752540,
      "count": "299"
    },
    {
      "date": 1584193812607,
      "count": "299"
    },
    {
      "date": 1584193872618,
      "count": "299"
    },
    {
      "date": 1584193932534,
      "count": "299"
    },
    {
      "date": 1584193992641,
      "count": "299"
    },
    {
      "date": 1584194053116,
      "count": "299"
    },
    {
      "date": 1584194112527,
      "count": "299"
    },
    {
      "date": 1584194172833,
      "count": "299"
    },
    {
      "date": 1584194232550,
      "count": "299"
    },
    {
      "date": 1584194292610,
      "count": "299"
    },
    {
      "date": 1584194352438,
      "count": "299"
    },
    {
      "date": 1584194412662,
      "count": "299"
    },
    {
      "date": 1584194472240,
      "count": "299"
    },
    {
      "date": 1584194652482,
      "count": "299"
    },
    {
      "date": 1584194712462,
      "count": "299"
    },
    {
      "date": 1584194772573,
      "count": "299"
    },
    {
      "date": 1584194832452,
      "count": "299"
    },
    {
      "date": 1584194952370,
      "count": "299"
    },
    {
      "date": 1584195012542,
      "count": "299"
    },
    {
      "date": 1584195072586,
      "count": "299"
    },
    {
      "date": 1584195192103,
      "count": "299"
    },
    {
      "date": 1584195314221,
      "count": "299"
    },
    {
      "date": 1584195373277,
      "count": "299"
    },
    {
      "date": 1584195431513,
      "count": "299"
    },
    {
      "date": 1584195493024,
      "count": "299"
    },
    {
      "date": 1584195553082,
      "count": "299"
    },
    {
      "date": 1584195610986,
      "count": "299"
    },
    {
      "date": 1584195671311,
      "count": "299"
    },
    {
      "date": 1584195730814,
      "count": "299"
    },
    {
      "date": 1584195792767,
      "count": "299"
    },
    {
      "date": 1584195852250,
      "count": "299"
    },
    {
      "date": 1584195912674,
      "count": "299"
    },
    {
      "date": 1584195972509,
      "count": "299"
    },
    {
      "date": 1584196033015,
      "count": "299"
    },
    {
      "date": 1584196092896,
      "count": "299"
    },
    {
      "date": 1584196152827,
      "count": "299"
    },
    {
      "date": 1584196212754,
      "count": "299"
    },
    {
      "date": 1584196273906,
      "count": "299"
    },
    {
      "date": 1584196332319,
      "count": "299"
    },
    {
      "date": 1584196392779,
      "count": "299"
    },
    {
      "date": 1584196452411,
      "count": "299"
    },
    {
      "date": 1584196512837,
      "count": "299"
    },
    {
      "date": 1584196572263,
      "count": "299"
    },
    {
      "date": 1584196632380,
      "count": "299"
    },
    {
      "date": 1584196692383,
      "count": "299"
    },
    {
      "date": 1584196752518,
      "count": "299"
    },
    {
      "date": 1584196812478,
      "count": "299"
    },
    {
      "date": 1584196873286,
      "count": "299"
    },
    {
      "date": 1584196933021,
      "count": "299"
    },
    {
      "date": 1584196992987,
      "count": "299"
    },
    {
      "date": 1584197052655,
      "count": "299"
    },
    {
      "date": 1584197112879,
      "count": "299"
    },
    {
      "date": 1584197172266,
      "count": "299"
    },
    {
      "date": 1584197231158,
      "count": "299"
    },
    {
      "date": 1584197292545,
      "count": "299"
    },
    {
      "date": 1584197413070,
      "count": "299"
    },
    {
      "date": 1584197472502,
      "count": "299"
    },
    {
      "date": 1584197532324,
      "count": "299"
    },
    {
      "date": 1584197592569,
      "count": "299"
    },
    {
      "date": 1584197652515,
      "count": "299"
    },
    {
      "date": 1584197712474,
      "count": "299"
    },
    {
      "date": 1584197772598,
      "count": "299"
    },
    {
      "date": 1584197832408,
      "count": "299"
    },
    {
      "date": 1584197892540,
      "count": "299"
    },
    {
      "date": 1584197952066,
      "count": "299"
    },
    {
      "date": 1584198012559,
      "count": "299"
    },
    {
      "date": 1584198073738,
      "count": "299"
    },
    {
      "date": 1584198132952,
      "count": "299"
    },
    {
      "date": 1584198192203,
      "count": "299"
    },
    {
      "date": 1584198252466,
      "count": "299"
    },
    {
      "date": 1584198312501,
      "count": "299"
    },
    {
      "date": 1584198372590,
      "count": "299"
    },
    {
      "date": 1584198432469,
      "count": "299"
    },
    {
      "date": 1584198492409,
      "count": "299"
    },
    {
      "date": 1584198552344,
      "count": "299"
    },
    {
      "date": 1584198612253,
      "count": "299"
    },
    {
      "date": 1584198672538,
      "count": "299"
    },
    {
      "date": 1584198732600,
      "count": "299"
    },
    {
      "date": 1584198852561,
      "count": "299"
    },
    {
      "date": 1584198912233,
      "count": "299"
    },
    {
      "date": 1584198972334,
      "count": "299"
    },
    {
      "date": 1584199032815,
      "count": "299"
    },
    {
      "date": 1584199092705,
      "count": "299"
    },
    {
      "date": 1584199152789,
      "count": "299"
    },
    {
      "date": 1584199212470,
      "count": "299"
    },
    {
      "date": 1584199272595,
      "count": "299"
    },
    {
      "date": 1584199332284,
      "count": "299"
    },
    {
      "date": 1584199392106,
      "count": "299"
    },
    {
      "date": 1584199452444,
      "count": "299"
    },
    {
      "date": 1584199512657,
      "count": "299"
    },
    {
      "date": 1584199573012,
      "count": "299"
    },
    {
      "date": 1584199632532,
      "count": "299"
    },
    {
      "date": 1584199692718,
      "count": "299"
    },
    {
      "date": 1584199752505,
      "count": "299"
    },
    {
      "date": 1584199812533,
      "count": "299"
    },
    {
      "date": 1584199872241,
      "count": "299"
    },
    {
      "date": 1584199932593,
      "count": "299"
    },
    {
      "date": 1584199992745,
      "count": "299"
    },
    {
      "date": 1584200052482,
      "count": "299"
    },
    {
      "date": 1584200112875,
      "count": "299"
    },
    {
      "date": 1584200172486,
      "count": "299"
    },
    {
      "date": 1584200232163,
      "count": "299"
    },
    {
      "date": 1584200291160,
      "count": "299"
    },
    {
      "date": 1584200352542,
      "count": "299"
    },
    {
      "date": 1584200472414,
      "count": "299"
    },
    {
      "date": 1584200532599,
      "count": "299"
    },
    {
      "date": 1584200592680,
      "count": "299"
    },
    {
      "date": 1584200652469,
      "count": "299"
    },
    {
      "date": 1584200713203,
      "count": "299"
    },
    {
      "date": 1584200772444,
      "count": "299"
    },
    {
      "date": 1584200893829,
      "count": "299"
    },
    {
      "date": 1584200952377,
      "count": "299"
    },
    {
      "date": 1584201012847,
      "count": "299"
    },
    {
      "date": 1584201072086,
      "count": "299"
    },
    {
      "date": 1584201132181,
      "count": "299"
    },
    {
      "date": 1584201192495,
      "count": "299"
    },
    {
      "date": 1584201252545,
      "count": "299"
    },
    {
      "date": 1584201312104,
      "count": "299"
    },
    {
      "date": 1584201372384,
      "count": "299"
    },
    {
      "date": 1584201432422,
      "count": "299"
    },
    {
      "date": 1584201492801,
      "count": "299"
    },
    {
      "date": 1584201554307,
      "count": "299"
    },
    {
      "date": 1584201612431,
      "count": "299"
    },
    {
      "date": 1584201672612,
      "count": "299"
    },
    {
      "date": 1584201734534,
      "count": "299"
    },
    {
      "date": 1584201792630,
      "count": "299"
    },
    {
      "date": 1584201852442,
      "count": "299"
    },
    {
      "date": 1584202034503,
      "count": "299"
    },
    {
      "date": 1584202092736,
      "count": "299"
    },
    {
      "date": 1584202152645,
      "count": "299"
    },
    {
      "date": 1584202212227,
      "count": "299"
    },
    {
      "date": 1584202272573,
      "count": "299"
    },
    {
      "date": 1584202332395,
      "count": "299"
    },
    {
      "date": 1584202392665,
      "count": "299"
    },
    {
      "date": 1584228437887,
      "count": "299"
    },
    {
      "date": 1584228492367,
      "count": "299"
    },
    {
      "date": 1584228612554,
      "count": "299"
    },
    {
      "date": 1584228672460,
      "count": "299"
    },
    {
      "date": 1584228732457,
      "count": "299"
    },
    {
      "date": 1584228792760,
      "count": "299"
    },
    {
      "date": 1584228852363,
      "count": "299"
    },
    {
      "date": 1584228912622,
      "count": "299"
    },
    {
      "date": 1584228972860,
      "count": "299"
    },
    {
      "date": 1584232214604,
      "count": "299"
    },
    {
      "date": 1584234015026,
      "count": "299"
    },
    {
      "date": 1584235816030,
      "count": "299"
    },
    {
      "date": 1584237614656,
      "count": "299"
    },
    {
      "date": 1584239415338,
      "count": "299"
    },
    {
      "date": 1584241215178,
      "count": "299"
    },
    {
      "date": 1584243014909,
      "count": "299"
    },
    {
      "date": 1584248412721,
      "count": "299"
    },
    {
      "date": 1584250212731,
      "count": "299"
    },
    {
      "date": 1584253812760,
      "count": "299"
    },
    {
      "date": 1584255612883,
      "count": "299"
    },
    {
      "date": 1584257413161,
      "count": "299"
    },
    {
      "date": 1584259212571,
      "count": "299"
    },
    {
      "date": 1584262812595,
      "count": "299"
    },
    {
      "date": 1584264612817,
      "count": "299"
    },
    {
      "date": 1584266413219,
      "count": "299"
    },
    {
      "date": 1584268212278,
      "count": "299"
    },
    {
      "date": 1584271812417,
      "count": "299"
    },
    {
      "date": 1584273612412,
      "count": "299"
    },
    {
      "date": 1584329415562,
      "count": "299"
    },
    {
      "date": 1584331215421,
      "count": "299"
    },
    {
      "date": 1584333017340,
      "count": "299"
    },
    {
      "date": 1584334815554,
      "count": "299"
    },
    {
      "date": 1584338414562,
      "count": "298"
    },
    {
      "date": 1584340214797,
      "count": "298"
    },
    {
      "date": 1584584876914,
      "count": "300"
    },
    {
      "date": 1584587306385,
      "count": "300"
    },
    {
      "date": 1584587335920,
      "count": "300"
    }
  ],
  "youtube": [
    {
      "date": 1581239175127,
      "count": "491"
    },
    {
      "date": 1581261135529,
      "count": "491"
    },
    {
      "date": 1581261192664,
      "count": "491"
    },
    {
      "date": 1581262214910,
      "count": "491"
    },
    {
      "date": 1581303617772,
      "count": "491"
    },
    {
      "date": 1581305416994,
      "count": "491"
    },
    {
      "date": 1581307216844,
      "count": "491"
    },
    {
      "date": 1581314412271,
      "count": "491"
    },
    {
      "date": 1581316217017,
      "count": "491"
    },
    {
      "date": 1581391820403,
      "count": "492"
    },
    {
      "date": 1582255093393,
      "count": "490"
    },
    {
      "date": 1582255152853,
      "count": "490"
    },
    {
      "date": 1582255212921,
      "count": "490"
    },
    {
      "date": 1582255272465,
      "count": "490"
    },
    {
      "date": 1582255816429,
      "count": "490"
    },
    {
      "date": 1582256413184,
      "count": "490"
    },
    {
      "date": 1582257016095,
      "count": "490"
    },
    {
      "date": 1582257617509,
      "count": "490"
    },
    {
      "date": 1582258094210,
      "count": "490"
    },
    {
      "date": 1582258153037,
      "count": "490"
    },
    {
      "date": 1584193218674,
      "count": "490"
    },
    {
      "date": 1584193272783,
      "count": "490"
    },
    {
      "date": 1584193334322,
      "count": "490"
    },
    {
      "date": 1584193392539,
      "count": "490"
    },
    {
      "date": 1584193452485,
      "count": "490"
    },
    {
      "date": 1584193512900,
      "count": "490"
    },
    {
      "date": 1584193572742,
      "count": "490"
    },
    {
      "date": 1584193632416,
      "count": "490"
    },
    {
      "date": 1584193692725,
      "count": "490"
    },
    {
      "date": 1584193752540,
      "count": "490"
    },
    {
      "date": 1584193812608,
      "count": "490"
    },
    {
      "date": 1584193872618,
      "count": "490"
    },
    {
      "date": 1584193932535,
      "count": "490"
    },
    {
      "date": 1584193992641,
      "count": "490"
    },
    {
      "date": 1584194053116,
      "count": "490"
    },
    {
      "date": 1584194112527,
      "count": "490"
    },
    {
      "date": 1584194172833,
      "count": "490"
    },
    {
      "date": 1584194232551,
      "count": "490"
    },
    {
      "date": 1584194292611,
      "count": "490"
    },
    {
      "date": 1584194352439,
      "count": "490"
    },
    {
      "date": 1584194412662,
      "count": "490"
    },
    {
      "date": 1584194472240,
      "count": "490"
    },
    {
      "date": 1584194652483,
      "count": "490"
    },
    {
      "date": 1584194712463,
      "count": "490"
    },
    {
      "date": 1584194772574,
      "count": "490"
    },
    {
      "date": 1584194832452,
      "count": "490"
    },
    {
      "date": 1584194952370,
      "count": "490"
    },
    {
      "date": 1584195012543,
      "count": "490"
    },
    {
      "date": 1584195072586,
      "count": "490"
    },
    {
      "date": 1584195192103,
      "count": "490"
    },
    {
      "date": 1584195314222,
      "count": "490"
    },
    {
      "date": 1584195373277,
      "count": "490"
    },
    {
      "date": 1584195431514,
      "count": "490"
    },
    {
      "date": 1584195493025,
      "count": "490"
    },
    {
      "date": 1584195553083,
      "count": "490"
    },
    {
      "date": 1584195610987,
      "count": "490"
    },
    {
      "date": 1584195671311,
      "count": "490"
    },
    {
      "date": 1584195730814,
      "count": "490"
    },
    {
      "date": 1584195792768,
      "count": "490"
    },
    {
      "date": 1584195852250,
      "count": "490"
    },
    {
      "date": 1584195912675,
      "count": "490"
    },
    {
      "date": 1584195972510,
      "count": "490"
    },
    {
      "date": 1584196033015,
      "count": "490"
    },
    {
      "date": 1584196092896,
      "count": "490"
    },
    {
      "date": 1584196152827,
      "count": "490"
    },
    {
      "date": 1584196212754,
      "count": "490"
    },
    {
      "date": 1584196273907,
      "count": "490"
    },
    {
      "date": 1584196332319,
      "count": "490"
    },
    {
      "date": 1584196392780,
      "count": "490"
    },
    {
      "date": 1584196452411,
      "count": "490"
    },
    {
      "date": 1584196512837,
      "count": "490"
    },
    {
      "date": 1584196572263,
      "count": "490"
    },
    {
      "date": 1584196632380,
      "count": "490"
    },
    {
      "date": 1584196692383,
      "count": "490"
    },
    {
      "date": 1584196752518,
      "count": "490"
    },
    {
      "date": 1584196812478,
      "count": "490"
    },
    {
      "date": 1584196873287,
      "count": "490"
    },
    {
      "date": 1584196933022,
      "count": "490"
    },
    {
      "date": 1584196992988,
      "count": "490"
    },
    {
      "date": 1584197052656,
      "count": "490"
    },
    {
      "date": 1584197112879,
      "count": "490"
    },
    {
      "date": 1584197172266,
      "count": "490"
    },
    {
      "date": 1584197231159,
      "count": "490"
    },
    {
      "date": 1584197292546,
      "count": "490"
    },
    {
      "date": 1584197413071,
      "count": "490"
    },
    {
      "date": 1584197472502,
      "count": "490"
    },
    {
      "date": 1584197532325,
      "count": "490"
    },
    {
      "date": 1584197592570,
      "count": "490"
    },
    {
      "date": 1584197652515,
      "count": "490"
    },
    {
      "date": 1584197712474,
      "count": "490"
    },
    {
      "date": 1584197772599,
      "count": "490"
    },
    {
      "date": 1584197832410,
      "count": "490"
    },
    {
      "date": 1584197892541,
      "count": "490"
    },
    {
      "date": 1584197952067,
      "count": "490"
    },
    {
      "date": 1584198012560,
      "count": "490"
    },
    {
      "date": 1584198073739,
      "count": "490"
    },
    {
      "date": 1584198132952,
      "count": "490"
    },
    {
      "date": 1584198192203,
      "count": "490"
    },
    {
      "date": 1584198252467,
      "count": "490"
    },
    {
      "date": 1584198312502,
      "count": "490"
    },
    {
      "date": 1584198372591,
      "count": "490"
    },
    {
      "date": 1584198432469,
      "count": "490"
    },
    {
      "date": 1584198492410,
      "count": "490"
    },
    {
      "date": 1584198552345,
      "count": "490"
    },
    {
      "date": 1584198612254,
      "count": "490"
    },
    {
      "date": 1584198672538,
      "count": "490"
    },
    {
      "date": 1584198732600,
      "count": "490"
    },
    {
      "date": 1584198852562,
      "count": "490"
    },
    {
      "date": 1584198912234,
      "count": "490"
    },
    {
      "date": 1584198972335,
      "count": "490"
    },
    {
      "date": 1584199032815,
      "count": "490"
    },
    {
      "date": 1584199092705,
      "count": "490"
    },
    {
      "date": 1584199152790,
      "count": "490"
    },
    {
      "date": 1584199212471,
      "count": "490"
    },
    {
      "date": 1584199272596,
      "count": "490"
    },
    {
      "date": 1584199332285,
      "count": "490"
    },
    {
      "date": 1584199392107,
      "count": "490"
    },
    {
      "date": 1584199452444,
      "count": "490"
    },
    {
      "date": 1584199512658,
      "count": "490"
    },
    {
      "date": 1584199573013,
      "count": "490"
    },
    {
      "date": 1584199632533,
      "count": "490"
    },
    {
      "date": 1584199692719,
      "count": "490"
    },
    {
      "date": 1584199752506,
      "count": "490"
    },
    {
      "date": 1584199812533,
      "count": "490"
    },
    {
      "date": 1584199872242,
      "count": "490"
    },
    {
      "date": 1584199932594,
      "count": "490"
    },
    {
      "date": 1584199992745,
      "count": "490"
    },
    {
      "date": 1584200052483,
      "count": "490"
    },
    {
      "date": 1584200112875,
      "count": "490"
    },
    {
      "date": 1584200172486,
      "count": "490"
    },
    {
      "date": 1584200232164,
      "count": "490"
    },
    {
      "date": 1584200291160,
      "count": "490"
    },
    {
      "date": 1584200352543,
      "count": "490"
    },
    {
      "date": 1584200472414,
      "count": "490"
    },
    {
      "date": 1584200532599,
      "count": "490"
    },
    {
      "date": 1584200592680,
      "count": "490"
    },
    {
      "date": 1584200652470,
      "count": "490"
    },
    {
      "date": 1584200713204,
      "count": "490"
    },
    {
      "date": 1584200772445,
      "count": "490"
    },
    {
      "date": 1584200893830,
      "count": "490"
    },
    {
      "date": 1584200952377,
      "count": "490"
    },
    {
      "date": 1584201012847,
      "count": "490"
    },
    {
      "date": 1584201072086,
      "count": "490"
    },
    {
      "date": 1584201132181,
      "count": "490"
    },
    {
      "date": 1584201192495,
      "count": "490"
    },
    {
      "date": 1584201252545,
      "count": "490"
    },
    {
      "date": 1584201312105,
      "count": "490"
    },
    {
      "date": 1584201372385,
      "count": "490"
    },
    {
      "date": 1584201432423,
      "count": "490"
    },
    {
      "date": 1584201492801,
      "count": "490"
    },
    {
      "date": 1584201554307,
      "count": "490"
    },
    {
      "date": 1584201612432,
      "count": "490"
    },
    {
      "date": 1584201672613,
      "count": "490"
    },
    {
      "date": 1584201734534,
      "count": "490"
    },
    {
      "date": 1584201792631,
      "count": "490"
    },
    {
      "date": 1584201852443,
      "count": "490"
    },
    {
      "date": 1584202034504,
      "count": "490"
    },
    {
      "date": 1584202092736,
      "count": "490"
    },
    {
      "date": 1584202152646,
      "count": "490"
    },
    {
      "date": 1584202212227,
      "count": "490"
    },
    {
      "date": 1584202272573,
      "count": "490"
    },
    {
      "date": 1584202332396,
      "count": "490"
    },
    {
      "date": 1584202392666,
      "count": "490"
    },
    {
      "date": 1584228437888,
      "count": "490"
    },
    {
      "date": 1584228492368,
      "count": "490"
    },
    {
      "date": 1584228612554,
      "count": "490"
    },
    {
      "date": 1584228672461,
      "count": "490"
    },
    {
      "date": 1584228732457,
      "count": "490"
    },
    {
      "date": 1584228792760,
      "count": "490"
    },
    {
      "date": 1584228852363,
      "count": "490"
    },
    {
      "date": 1584228912623,
      "count": "490"
    },
    {
      "date": 1584228972861,
      "count": "490"
    },
    {
      "date": 1584232214605,
      "count": "490"
    },
    {
      "date": 1584234015027,
      "count": "490"
    },
    {
      "date": 1584235816030,
      "count": "490"
    },
    {
      "date": 1584237614656,
      "count": "490"
    },
    {
      "date": 1584239415339,
      "count": "490"
    },
    {
      "date": 1584241215179,
      "count": "490"
    },
    {
      "date": 1584243014910,
      "count": "490"
    },
    {
      "date": 1584248412722,
      "count": "490"
    },
    {
      "date": 1584250212732,
      "count": "490"
    },
    {
      "date": 1584253812761,
      "count": "490"
    },
    {
      "date": 1584255612884,
      "count": "490"
    },
    {
      "date": 1584257413162,
      "count": "490"
    },
    {
      "date": 1584259212574,
      "count": "490"
    },
    {
      "date": 1584262812596,
      "count": "490"
    },
    {
      "date": 1584264612818,
      "count": "490"
    },
    {
      "date": 1584266413220,
      "count": "490"
    },
    {
      "date": 1584268212280,
      "count": "490"
    },
    {
      "date": 1584271812417,
      "count": "490"
    },
    {
      "date": 1584273612413,
      "count": "490"
    },
    {
      "date": 1584329415563,
      "count": "490"
    },
    {
      "date": 1584331215422,
      "count": "490"
    },
    {
      "date": 1584333017341,
      "count": "490"
    },
    {
      "date": 1584334815555,
      "count": "490"
    },
    {
      "date": 1584338414562,
      "count": "490"
    },
    {
      "date": 1584340214798,
      "count": "490"
    },
    {
      "date": 1584584876914,
      "count": "490"
    },
    {
      "date": 1584587306385,
      "count": "490"
    },
    {
      "date": 1584587335921,
      "count": "490"
    }
  ]
}